blob_storage_jatin/__init__.py
blob_storage_jatin/blob_conn.py
blob_storage_jatin/config.py
blob_storage_jatin-0.0.2.dist-info/LICENSE
blob_storage_jatin-0.0.2.dist-info/METADATA
blob_storage_jatin-0.0.2.dist-info/WHEEL
blob_storage_jatin-0.0.2.dist-info/top_level.txt
blob_storage_jatin-0.0.2.dist-info/RECORD
