Metadata-Version: 2.1
Name: blob-storage-jatin
Version: 0.0.2
Summary: A Blob Storage Package for configuring Azure Blob Storage Account and access it.
Author-email: Jatin Talati <jatalati@in.ibm.com>
Keywords: blob,storage,blobstorage,azure
Classifier: Programming Language :: Python :: 3
Classifier: Development Status :: 1 - Planning
Classifier: Operating System :: OS Independent
Requires-Python: >=3.7
License-File: LICENSE
Requires-Dist: azure-core
Requires-Dist: azure-storage-blob
Requires-Dist: httpcore
Requires-Dist: httpx
Requires-Dist: oauthlib
Requires-Dist: okta-jwt
Requires-Dist: pydantic
Requires-Dist: PyJWT
Requires-Dist: python-jose
Requires-Dist: requests
Requires-Dist: requests-oauthlib
Requires-Dist: toml
